Metadata-Version: 2.4
Name: pyQuantumAI
Version: 1.3.108
Summary: Квантовая AI педагогика: Призма, Эквалайзер, Пирамида, Retrain - полный цикл обучения через квантовый резонанс
Home-page: https://gitlab.com/antondodonov/libEqualizer
Author: NativeMind & УРАБИ.РФ
Author-email: "NativeMind & УРАБИ.РФ" <info@ураби.рф>
Maintainer-email: Anton Dodonov <info@ураби.рф>
License: NativeMindNONC
Project-URL: Homepage, https://gitlab.com/antondodonov/libEqualizer
Project-URL: Documentation, https://gitlab.com/antondodonov/libEqualizer/wiki
Project-URL: Repository, https://gitlab.com/antondodonov/libEqualizer.git
Project-URL: Bug Tracker, https://gitlab.com/antondodonov/libEqualizer/issues
Keywords: ai,machine-learning,quantum-computing,model-synchronization,transformers,peft,lora,prisma,equalizer,pyramid,retrain,import-substitution,russian-ai,108
Classifier: Development Status :: 4 - Beta
Classifier: Intended Audience :: Developers
Classifier: Intended Audience :: Science/Research
Classifier: Topic :: Scientific/Engineering :: Artificial Intelligence
Classifier: License :: Other/Proprietary License
Classifier: Programming Language :: Python :: 3
Classifier: Programming Language :: Python :: 3.8
Classifier: Programming Language :: Python :: 3.9
Classifier: Programming Language :: Python :: 3.10
Classifier: Programming Language :: Python :: 3.11
Classifier: Programming Language :: Python :: 3.12
Classifier: Programming Language :: Python :: 3.13
Classifier: Operating System :: OS Independent
Requires-Python: >=3.8
License-File: LICENSE
Requires-Dist: torch>=1.13.0
Requires-Dist: numpy>=1.21.0
Requires-Dist: transformers>=4.30.0
Requires-Dist: peft>=0.4.0
Requires-Dist: safetensors>=0.3.0
Provides-Extra: dev
Requires-Dist: pytest>=7.0.0; extra == "dev"
Requires-Dist: pytest-cov>=4.0.0; extra == "dev"
Requires-Dist: black>=23.0.0; extra == "dev"
Requires-Dist: flake8>=6.0.0; extra == "dev"
Requires-Dist: mypy>=1.0.0; extra == "dev"
Provides-Extra: crypto
Requires-Dist: cryptography>=41.0.0; extra == "crypto"
Provides-Extra: all
Requires-Dist: libequalizer[crypto,dev]; extra == "all"
Dynamic: author
Dynamic: home-page
Dynamic: license-file
Dynamic: requires-python
